<?xml version="1.0" standalone="yes"?>
<NewDataSet>
  <xs:schema id="NewDataSet" xmlns="" xmlns:xs="http://www.w3.org/2001/XMLSchema" xmlns:msdata="urn:schemas-microsoft-com:xml-msdata">
    <xs:element name="XML">
      <xs:complexType>
        <xs:sequence>
          <xs:element name="IdParam" msdata:Caption="" type="xs:string" />
          <xs:element name="Value" msdata:Caption="" type="xs:string" minOccurs="0" />
          <xs:element name="Visual" msdata:Caption="" type="xs:boolean" minOccurs="0" />
          <xs:element name="Title" msdata:Caption="" type="xs:string" minOccurs="0" />
          <xs:element name="UserLevel" msdata:Caption="" type="xs:int" minOccurs="0" />
          <xs:element name="Category" msdata:Caption="" type="xs:string" minOccurs="0" />
          <xs:element name="SortIndex" msdata:Caption="" type="xs:double" minOccurs="0" />
          <xs:element name="Unit" msdata:Caption="" type="xs:string" minOccurs="0" />
          <xs:element name="Error" msdata:Caption="" type="xs:string" minOccurs="0" />
        </xs:sequence>
      </xs:complexType>
    </xs:element>
    <xs:element name="NewDataSet" msdata:IsDataSet="true" msdata:MainDataTable="XML" msdata:UseCurrentLocale="true">
      <xs:complexType>
        <xs:choice minOccurs="0" maxOccurs="unbounded">
          <xs:element ref="XML" />
        </xs:choice>
      </xs:complexType>
      <xs:unique name="Constraint1" msdata:PrimaryKey="true">
        <xs:selector xpath=".//XML" />
        <xs:field xpath="IdParam" />
      </xs:unique>
    </xs:element>
  </xs:schema>
</NewDataSet>